<prescription xmlns="http://greenify.github.io/schemas/prescription/v3"
  type="broadcast" package="com.tencent.qqlite" class="com.tencent.mobileqq.statistics.Reportbroadcast" sender="any">
</prescription>

<prescription xmlns="http://greenify.github.io/schemas/prescription/v3"
  type="broadcast" package="com.tencent.qqlite" class="cooperation.plugin.PluginCrashbroadcast" sender="any">
</prescription>

<prescription xmlns="http://greenify.github.io/schemas/prescription/v3"
  type="broadcast" package="com.tencent.qqlite" class="cooperation.qqfav.QfavPluginProxybroadcast" sender="any">
</prescription>

<prescription xmlns="http://greenify.github.io/schemas/prescription/v3"
  type="broadcast" package="com.tencent.qqlite" class="com.tencent.mobileqq.webprocess.WebProcessbroadcast" sender="any">
</prescription>

<prescription xmlns="http://greenify.github.io/schemas/prescription/v3"
  type="broadcast" package="com.tencent.qqlite" class="com.tencent.mobileqq.mini.app.InternalAppBrandTaskPreloadbroadcast" sender="any">
</prescription>

<prescription xmlns="http://greenify.github.io/schemas/prescription/v3"
  type="broadcast" package="com.tencent.qqlite" class="com.tencent.mobileqq.mini.app.AppBrandTaskPreloadbroadcast" sender="any">
</prescription>

<prescription xmlns="http://greenify.github.io/schemas/prescription/v3"
  type="broadcast" package="com.tencent.qqlite" class="com.tencent.mobileqq.mini.app.AppBrandTaskPreloadbroadcast1" sender="any">
</prescription>

<prescription xmlns="http://greenify.github.io/schemas/prescription/v3"
  type="broadcast" package="com.tencent.qqlite" class="com.tencent.mobileqq.mini.app.AppBrandTaskPreloadbroadcast2" sender="any">
</prescription>

<prescription xmlns="http://greenify.github.io/schemas/prescription/v3"
  type="broadcast" package="com.tencent.qqlite" class="com.tencent.mobileqq.mini.app.AppBrandTaskPreloadbroadcast3" sender="any">
</prescription>

<prescription xmlns="http://greenify.github.io/schemas/prescription/v3"
  type="broadcast" package="com.tencent.qqlite" class="com.tencent.mobileqq.mini.app.AppBrandTaskPreloadbroadcast3" sender="any">
</prescription>


<prescription xmlns="http://greenify.github.io/schemas/prescription/v3"
  type="broadcast" package="com.tencent.qqlite" class="com.tencent.mobileqq.mini.app.AppBrandTaskPreloadbroadcast4" sender="any">
</prescription>


<prescription xmlns="http://greenify.github.io/schemas/prescription/v3"
  type="broadcast" package="com.tencent.qqlite" class="com.tencent.mobileqq.mini.app.AppBrandTaskPreloadbroadcast5" sender="any">
</prescription>


<prescription xmlns="http://greenify.github.io/schemas/prescription/v3"
  type="broadcast" package="com.tencent.qqlite" class="com.tencent.mobileqq.filemanager.core.UniformDownloadNfnbroadcast" sender="any">
</prescription>


<prescription xmlns="http://greenify.github.io/schemas/prescription/v3"
  type="broadcast" package="com.tencent.qqlite" class="com.tencent.open.downloadnew.common.Downloadbroadcast" sender="any">
</prescription>

<prescription xmlns="http://greenify.github.io/schemas/prescription/v3"
  type="broadcast" package="com.tencent.qqlite" class="com.tencent.open.downloadnew.common.DownloadbroadcastWebProcess" sender="any">
</prescription>

<prescription xmlns="http://greenify.github.io/schemas/prescription/v3"
  type="broadcast" package="com.tencent.qqlite" class="com.tencent.open.business.base.appreport.AppReportbroadcast" sender="any">
</prescription>

<prescription xmlns="http://greenify.github.io/schemas/prescription/v3"
  type="broadcast" package="com.tencent.qqlite" class="com.tencent.qav.app.QavAwakebroadcast" sender="any">
</prescription>

<prescription xmlns="http://greenify.github.io/schemas/prescription/v3"
  type="service" package="com.tencent.qqlite" class="com.tencent.mobileqq.pluginsdk.ipc.PluginRemoteService$Sub1" sender="any">
</prescription>

<prescription xmlns="http://greenify.github.io/schemas/prescription/v3"
  type="service" package="com.tencent.qqlite" class="com.tencent.mobileqq.pluginsdk.ipc.PluginRemoteService$Sub2" sender="any">
</prescription>

<prescription xmlns="http://greenify.github.io/schemas/prescription/v3"
  type="service" package="com.tencent.qqlite" class="com.tencent.mobileqq.contactsync.syncadapter.SyncService" sender="any">
</prescription>

<prescription xmlns="http://greenify.github.io/schemas/prescription/v3"
  type="service" package="com.tencent.qqlite" class="cooperation.qzone.QzonePictureViewerProxyService" sender="any">
</prescription>

<prescription xmlns="http://greenify.github.io/schemas/prescription/v3"
  type="service" package="com.tencent.qqlite" class="com.tencent.tmassistantsdk.downloadservice.TMAssistantDownloadSDKService" sender="any">
</prescription>

<prescription xmlns="http://greenify.github.io/schemas/prescription/v3"
  type="service" package="com.tencent.qqlite" class="cooperation.qwallet.plugin.QWalletPluginProxyService" sender="any">
</prescription>

<prescription xmlns="http://greenify.github.io/schemas/prescription/v3"
  type="service" package="com.tencent.qqlite" class="com.tencent.biz.troop.TroopMemberApiService" sender="any">
</prescription>

<prescription xmlns="http://greenify.github.io/schemas/prescription/v3"
  type="service" package="com.tencent.qqlite" class="com.tencent.qav.ipc.QavService" sender="any">
</prescription>

<prescription xmlns="http://greenify.github.io/schemas/prescription/v3"
  type="activity" package="com.tencent.qqlite" class="com.tencent.mobileqq.activity.UpgradeActivity" sender="any">
</prescription>

<prescription xmlns="http://greenify.github.io/schemas/prescription/v3"
  type="activity" package="com.tencent.qqlite" class="com.tencent.mobileqq.activity.UpgradeDetailActivity" sender="any">
</prescription>



